streamlit_meta_state/__init__.py
streamlit_meta_state/core.py
streamlit_meta_state-0.1.3.dist-info/LICENSE
streamlit_meta_state-0.1.3.dist-info/METADATA
streamlit_meta_state-0.1.3.dist-info/WHEEL
streamlit_meta_state-0.1.3.dist-info/top_level.txt
streamlit_meta_state-0.1.3.dist-info/RECORD
