Metadata-Version: 2.2
Name: streamlit-meta-state
Version: 0.1.3
Summary: A Streamlit module for session state management
Home-page: https://github.com/igormicadei/streamlit-meta-state
Author: Igor Micadei
Author-email: Igor Micadei <i.micadei@gmail.com>
License: MIT
Project-URL: Homepage, https://github.com/igormicadei/streamlit-meta-state
Project-URL: Issues, https://github.com/igormicadei/streamlit-meta-state/issues
Classifier: Programming Language :: Python :: 3
Classifier: License :: OSI Approved :: MIT License
Classifier: Operating System :: OS Independent
Requires-Python: >=3.8
License-File: LICENSE
Dynamic: author
Dynamic: home-page
Dynamic: requires-python
